{
    "name": "unary_add",
    "alphabet": ["1", ".", "_"],
    "blank": "_",
    "states": ["scanright", "to_end", "cleanup", "HALT"],
    "initial": "scanright",
    "finals": ["HALT"],
    "transitions": {
        "scanright": [
            { "read": "1", "to_state": "scanright", "write": "1", "action": "RIGHT" },
            { "read": ".", "to_state": "to_end",    "write": "1", "action": "RIGHT" }
        ],
        "to_end": [
            { "read": "1", "to_state": "to_end",    "write": "1", "action": "RIGHT" },
            { "read": "_", "to_state": "cleanup",   "write": "_", "action": "LEFT" }
        ],
        "cleanup": [
            { "read": "1", "to_state": "HALT",      "write": "_", "action": "LEFT" }
        ]
    }
}